setup.py
src/gs2_cdk/__init__.py
src/gs2_cdk.egg-info/PKG-INFO
src/gs2_cdk.egg-info/SOURCES.txt
src/gs2_cdk.egg-info/dependency_links.txt
src/gs2_cdk.egg-info/top_level.txt
src/gs2_cdk/account/__init__.py
src/gs2_cdk/account/model/BanStatus.py
src/gs2_cdk/account/model/CurrentMasterData.py
src/gs2_cdk/account/model/Namespace.py
src/gs2_cdk/account/model/OpenIdConnectSetting.py
src/gs2_cdk/account/model/PlatformUser.py
src/gs2_cdk/account/model/ScopeValue.py
src/gs2_cdk/account/model/TakeOverTypeModel.py
src/gs2_cdk/account/model/__init__.py
src/gs2_cdk/account/ref/BanStatusRef.py
src/gs2_cdk/account/ref/MasterDataVersionRef.py
src/gs2_cdk/account/ref/NamespaceRef.py
src/gs2_cdk/account/ref/TakeOverTypeModelRef.py
src/gs2_cdk/account/ref/__init__.py
src/gs2_cdk/account/stamp_sheet/__init__.py
src/gs2_cdk/ad_reward/__init__.py
src/gs2_cdk/ad_reward/model/AdMob.py
src/gs2_cdk/ad_reward/model/AppLovinMax.py
src/gs2_cdk/ad_reward/model/Namespace.py
src/gs2_cdk/ad_reward/model/UnityAd.py
src/gs2_cdk/ad_reward/model/__init__.py
src/gs2_cdk/ad_reward/ref/NamespaceRef.py
src/gs2_cdk/ad_reward/ref/__init__.py
src/gs2_cdk/ad_reward/stamp_sheet/AcquirePointByUserId.py
src/gs2_cdk/ad_reward/stamp_sheet/ConsumePointByUserId.py
src/gs2_cdk/ad_reward/stamp_sheet/__init__.py
src/gs2_cdk/auth/__init__.py
src/gs2_cdk/auth/model/AccessToken.py
src/gs2_cdk/auth/model/__init__.py
src/gs2_cdk/auth/ref/__init__.py
src/gs2_cdk/auth/stamp_sheet/__init__.py
src/gs2_cdk/buff/__init__.py
src/gs2_cdk/buff/model/BuffEntryModel.py
src/gs2_cdk/buff/model/BuffTargetAction.py
src/gs2_cdk/buff/model/BuffTargetGrn.py
src/gs2_cdk/buff/model/BuffTargetModel.py
src/gs2_cdk/buff/model/CurrentMasterData.py
src/gs2_cdk/buff/model/Namespace.py
src/gs2_cdk/buff/model/OverrideBuffRate.py
src/gs2_cdk/buff/model/__init__.py
src/gs2_cdk/buff/ref/BuffEntryModelRef.py
src/gs2_cdk/buff/ref/MasterDataVersionRef.py
src/gs2_cdk/buff/ref/NamespaceRef.py
src/gs2_cdk/buff/ref/__init__.py
src/gs2_cdk/buff/stamp_sheet/__init__.py
src/gs2_cdk/chat/__init__.py
src/gs2_cdk/chat/model/CategoryModel.py
src/gs2_cdk/chat/model/CurrentMasterData.py
