Metadata-Version: 2.4
Name: gs2-cdk
Version: 1.0.120
Summary: GS2 SDK for Python.
Home-page: https://gs2.io/
Author: Game Server Services, Inc.
Author-email: contact@gs2.io
License: Apache License 2.0
Classifier: Programming Language :: Python
Classifier: Programming Language :: Python :: 3
Classifier: Programming Language :: Python :: 3.6
Dynamic: author
Dynamic: author-email
Dynamic: classifier
Dynamic: home-page
Dynamic: license
Dynamic: summary
